estrapy/__init__.py
estrapy/__main__.py
estrapy/estrapy.py
estrapy/parser.py
estrapy/commands/__init__.py
estrapy/commands/_context.py
estrapy/commands/_exceptions.py
estrapy/commands/_format.py
estrapy/commands/_handler.py
estrapy/commands/_misc.py
estrapy/commands/_numberunit.py
estrapy/commands/_parser.py
estrapy/commands/average.py
estrapy/commands/background.py
estrapy/commands/edge.py
estrapy/commands/filein.py
estrapy/commands/fit.py
estrapy/commands/fourier.py
estrapy/commands/glitch.py
estrapy/commands/othercmds.py
estrapy/commands/pca.py
estrapy/commands/phase.py
estrapy/commands/plot.py
estrapy/commands/postedge.py
estrapy/commands/preedge.py
estrapy/commands/save.py
estrapy-1.0.6.dist-info/licenses/LICENSE
estrapy-1.0.6.dist-info/METADATA
estrapy-1.0.6.dist-info/WHEEL
estrapy-1.0.6.dist-info/entry_points.txt
estrapy-1.0.6.dist-info/top_level.txt
estrapy-1.0.6.dist-info/RECORD
