Metadata-Version: 2.4
Name: EstraPy
Version: 1.0.6
Summary: An input-file oriented EXAFS analysis toolbox
Home-page: https://github.com/ramsteak/estrapy
Author: Marco Stecca, Carlo Meneghini, Paolo Centomo
License: MIT License
Keywords: estrapy,syncrotron,xray,exafs,xas,xanes
Classifier: Programming Language :: Python :: 3
Classifier: License :: OSI Approved :: MIT License
Requires-Python: >=3.12
License-File: LICENSE
Requires-Dist: scipy
Requires-Dist: matplotlib
Requires-Dist: pandas
Requires-Dist: statsmodels
Requires-Dist: xraydb
Requires-Dist: colorlog
Provides-Extra: test
Requires-Dist: pytest; extra == "test"
Requires-Dist: pytest-cov; extra == "test"
Dynamic: license-file
